kfinance.py
kfinance-0.1.1.dist-info/METADATA
kfinance-0.1.1.dist-info/WHEEL
kfinance-0.1.1.dist-info/top_level.txt
kfinance-0.1.1.dist-info/RECORD
