Metadata-Version: 2.1
Name: kfinance
Version: 0.1.1
Summary: Python package for Korea finance
Author-email: Jungwoo Yang <jwyang0213@gmail.com>
License: MIT
